pals/__init__.py
pals/core.py
pals/version.py
pals/tests/test_core.py
PALs-0.4.0.dist-info/METADATA
PALs-0.4.0.dist-info/WHEEL
PALs-0.4.0.dist-info/top_level.txt
PALs-0.4.0.dist-info/RECORD
