Metadata-Version: 2.1
Name: PALs
Version: 0.4.0
Summary: Easy distributed locking using PostgreSQL Advisory Locks.
Home-page: https://github.com/level12/pals
Author: Randy Syring
Author-email: randy.syring@level12.io
License: BSD-3-Clause
Platform: UNKNOWN
Classifier: Development Status :: 4 - Beta
Classifier: Intended Audience :: Developers
Classifier: License :: OSI Approved :: BSD License
Classifier: Operating System :: OS Independent
Classifier: Programming Language :: Python :: 3
Classifier: Programming Language :: Python :: 3.7
Classifier: Programming Language :: Python :: 3.8
Classifier: Programming Language :: Python :: 3.9
Classifier: Programming Language :: Python :: 3.10
Requires-Dist: sqlalchemy
Provides-Extra: tests
Requires-Dist: pytest ; extra == 'tests'
Requires-Dist: pytest-cov ; extra == 'tests'
Requires-Dist: psycopg[binary] ; extra == 'tests'
